{
    "DATACENTERS": [
        {
            "name": "Node1",
            "hosts": 55,
            "host_spec": {
                "HOST_PES": 128,
                "HOST_MIPS": 2400000,
                "HOST_RAM": 128000,
                "HOST_BW": 10000000,
                "HOST_STORAGE": 500000000000
            },
            "vm": 20,
            "vm_spec": {
                "VM_PES": 2,
                "VM_RAM": 8192,
                "VM_BW": 500000,
                "VM_STORAGE": 1000000
            },
            "cloudlets": 40,
            "cloudlet_spec": {
                "CLOUDLET_LENGTH": 100000000,
                "CLOUDLET_PES": 2,
                "FILE_SIZE": 2048,
                "OUTPUT_SIZE": 2048
            },
            "power_spec": {
                "HOST_START_UP_DELAY": 0.2,
                "HOST_SHUT_DOWN_DELAY": 0.1,
                "HOST_START_UP_POWER": 5.0,
                "HOST_SHUT_DOWN_POWER": 3.0,
                "STATIC_POWER": 100.0,
                "MAX_POWER": 1000.0
            }
        },
        {
            "name": "Node2",
            "hosts": 55,
            "host_spec": {
                "HOST_PES": 128,
                "HOST_MIPS": 2400000,
                "HOST_RAM": 128000,
                "HOST_BW": 10000000,
                "HOST_STORAGE": 500000000000
            },
            "vm": 20,
            "vm_spec": {
                "VM_PES": 2,
                "VM_RAM": 8192,
                "VM_BW": 500000,
                "VM_STORAGE": 1000000
            },
            "cloudlets": 40,
            "cloudlet_spec": {
                "CLOUDLET_LENGTH": 100000000,
                "CLOUDLET_PES": 2,
                "FILE_SIZE": 2048,
                "OUTPUT_SIZE": 2048
            },
            "power_spec": {
                "HOST_START_UP_DELAY": 0.2,
                "HOST_SHUT_DOWN_DELAY": 0.1,
                "HOST_START_UP_POWER": 5.0,
                "HOST_SHUT_DOWN_POWER": 3.0,
                "STATIC_POWER": 100.0,
                "MAX_POWER": 1000.0
            }
        },
        {
            "name": "Node3",
            "hosts": 55,
            "host_spec": {
                "HOST_PES": 128,
                "HOST_MIPS": 2400000,
                "HOST_RAM": 128000,
                "HOST_BW": 10000000,
                "HOST_STORAGE": 500000000000
            },
            "vm": 20,
            "vm_spec": {
                "VM_PES": 2,
                "VM_RAM": 8192,
                "VM_BW": 500000,
                "VM_STORAGE": 1000000
            },
            "cloudlets": 40,
            "cloudlet_spec": {
                "CLOUDLET_LENGTH": 100000000,
                "CLOUDLET_PES": 2,
                "FILE_SIZE": 2048,
                "OUTPUT_SIZE": 2048
            },
            "power_spec": {
                "HOST_START_UP_DELAY": 0.2,
                "HOST_SHUT_DOWN_DELAY": 0.1,
                "HOST_START_UP_POWER": 5.0,
                "HOST_SHUT_DOWN_POWER": 3.0,
                "STATIC_POWER": 100.0,
                "MAX_POWER": 1000.0
            }
        }
    ]
}
